odoo/addons/account_spread_contract/README.rst
odoo/addons/account_spread_contract/__init__.py
odoo/addons/account_spread_contract/__manifest__.py
odoo/addons/account_spread_contract/i18n/account_spread_contract.pot
odoo/addons/account_spread_contract/i18n/nl.po
odoo/addons/account_spread_contract/models/__init__.py
odoo/addons/account_spread_contract/models/account_analytic_account.py
odoo/addons/account_spread_contract/models/account_analytic_invoice_line.py
odoo/addons/account_spread_contract/models/account_spread_template.py
odoo/addons/account_spread_contract/readme/CONFIGURE.rst
odoo/addons/account_spread_contract/readme/CONTRIBUTORS.rst
odoo/addons/account_spread_contract/readme/DESCRIPTION.rst
odoo/addons/account_spread_contract/readme/HISTORY.rst
odoo/addons/account_spread_contract/readme/USAGE.rst
odoo/addons/account_spread_contract/static/description/icon.png
odoo/addons/account_spread_contract/static/description/index.html
odoo/addons/account_spread_contract/tests/__init__.py
odoo/addons/account_spread_contract/tests/test_account_spread_contract.py
odoo/addons/account_spread_contract/views/account_analytic_account.xml
odoo/addons/account_spread_contract/views/account_spread_template.xml
odoo/addons/account_spread_contract/wizards/__init__.py
odoo/addons/account_spread_contract/wizards/account_spread_contract_line_link_wizard.py
odoo/addons/account_spread_contract/wizards/account_spread_contract_line_link_wizard.xml
odoo11_addon_account_spread_contract-11.0.1.0.0.99.dev5.dist-info/METADATA
odoo11_addon_account_spread_contract-11.0.1.0.0.99.dev5.dist-info/WHEEL
odoo11_addon_account_spread_contract-11.0.1.0.0.99.dev5.dist-info/top_level.txt
odoo11_addon_account_spread_contract-11.0.1.0.0.99.dev5.dist-info/RECORD
